onspy/__init__.py
onspy/browse.py
onspy/client.py
onspy/code_lists.py
onspy/datasets.py
onspy/exceptions.py
onspy/get.py
onspy/search.py
onspy/utils.py
onspy-0.1.2.dist-info/licenses/LICENSE
onspy-0.1.2.dist-info/METADATA
onspy-0.1.2.dist-info/WHEEL
onspy-0.1.2.dist-info/top_level.txt
onspy-0.1.2.dist-info/RECORD
