Metadata-Version: 2.4
Name: onspy
Version: 0.1.2
Summary: Python client for the Office of National Statistics (ONS) API
Author: Joe Wait
License: GNU General Public License
Project-URL: Homepage, https://github.com/Joe-Wait/onspy
Project-URL: Bug Tracker, https://github.com/Joe-Wait/onspy/issues
Project-URL: Documentation, https://github.com/Joe-Wait/onspy
Keywords: ons,statistics,data,api,uk,office for national statistics
Classifier: Programming Language :: Python :: 3
Classifier: Programming Language :: Python :: 3.7
Classifier: Programming Language :: Python :: 3.8
Classifier: Programming Language :: Python :: 3.9
Classifier: Programming Language :: Python :: 3.10
Classifier: Operating System :: OS Independent
Classifier: Development Status :: 4 - Beta
Classifier: Intended Audience :: Developers
Classifier: Intended Audience :: Science/Research
Classifier: Topic :: Scientific/Engineering :: Information Analysis
Requires-Python: >=3.7
License-File: LICENSE
Requires-Dist: pandas>=1.0.0
Requires-Dist: requests>=2.25.0
Dynamic: license-file
